aeronet_vector/__init__.py
aeronet_vector/__version__.py
aeronet_vector/feature.py
aeronet_vector/featurecollection.py
aeronet_vector/merge.py
aeronet_vector/utils.py
aeronet_vector-0.2.5.dist-info/METADATA
aeronet_vector-0.2.5.dist-info/WHEEL
aeronet_vector-0.2.5.dist-info/top_level.txt
aeronet_vector-0.2.5.dist-info/RECORD
