Metadata-Version: 2.1
Name: aeronet-vector
Version: 0.2.5
Summary: Vector operations for aeronetlib. Based on shapely + r-tree indexing
Home-page: 
Author: Geoalert
Author-email: hello@geoalert.io
License: MIT
Classifier: License :: OSI Approved :: MIT License
Classifier: Programming Language :: Python
Classifier: Programming Language :: Python :: 3
Classifier: Programming Language :: Python :: 3.6
Classifier: Programming Language :: Python :: Implementation :: CPython
Classifier: Programming Language :: Python :: Implementation :: PyPy
Requires-Python: >=3.6.0
Requires-Dist: rasterio >=1.0.0
Requires-Dist: rtree >=0.8.3
Requires-Dist: shapely >=1.7.1
Requires-Dist: tqdm <4.65,>=4.36.1
